{
	"__inputs": [
	  {
		"name": "DS_PROMETHEUS",
		"label": "Prometheus",
		"description": "",
		"type": "datasource",
		"pluginId": "prometheus",
		"pluginName": "Prometheus"
	  }
	],
	"__elements": {},
	"__requires": [
	  {
		"type": "panel",
		"id": "gauge",
		"name": "Gauge",
		"version": ""
	  },
	  {
		"type": "panel",
		"id": "geomap",
		"name": "Geomap",
		"version": ""
	  },
	  {
		"type": "grafana",
		"id": "grafana",
		"name": "Grafana",
		"version": "9.2.4"
	  },
	  {
		"type": "panel",
		"id": "piechart",
		"name": "Pie chart",
		"version": ""
	  },
	  {
		"type": "datasource",
		"id": "prometheus",
		"name": "Prometheus",
		"version": "1.0.0"
	  },
	  {
		"type": "panel",
		"id": "timeseries",
		"name": "Time series",
		"version": ""
	  }
	],
	"annotations": {
	  "list": [
		{
		  "builtIn": 1,
		  "datasource": {
			"type": "grafana",
			"uid": "-- Grafana --"
		  },
		  "enable": true,
		  "hide": true,
		  "iconColor": "rgba(0, 211, 255, 1)",
		  "name": "Annotations & Alerts",
		  "target": {
			"limit": 100,
			"matchAny": false,
			"tags": [],
			"type": "dashboard"
		  },
		  "type": "dashboard"
		}
	  ]
	},
	"description": "Leveraging eBPF and XDP for monitoring",
	"editable": true,
	"fiscalYearStartMonth": 0,
	"graphTooltip": 0,
	"id": null,
	"links": [],
	"liveNow": false,
	"panels": [
	  {
		"datasource": {
		  "type": "prometheus",
		  "uid": "${DS_PROMETHEUS}"
		},
		"fieldConfig": {
		  "defaults": {
			"color": {
			  "mode": "thresholds"
			},
			"custom": {
			  "hideFrom": {
				"legend": false,
				"tooltip": false,
				"viz": false
			  }
			},
			"mappings": [],
			"thresholds": {
			  "mode": "percentage",
			  "steps": [
				{
				  "color": "green",
				  "value": null
				}
			  ]
			}
		  },
		  "overrides": []
		},
		"gridPos": {
		  "h": 24,
		  "w": 16,
		  "x": 0,
		  "y": 0
		},
		"id": 4,
		"options": {
		  "basemap": {
			"config": {},
			"name": "Layer 0",
			"type": "default"
		  },
		  "controls": {
			"mouseWheelZoom": true,
			"showAttribution": true,
			"showDebug": false,
			"showMeasure": false,
			"showScale": false,
			"showZoom": true
		  },
		  "layers": [
			{
			  "config": {
				"blur": 18,
				"radius": 3,
				"weight": {
				  "fixed": 1,
				  "max": 1,
				  "min": 0
				}
			  },
			  "name": "Layer 2",
			  "opacity": 0.5,
			  "tooltip": true,
			  "type": "heatmap"
			}
		  ],
		  "tooltip": {
			"mode": "details"
		  },
		  "view": {
			"allLayers": true,
			"id": "coords",
			"lastOnly": false,
			"lat": 51.395122,
			"layer": "Layer 1",
			"lon": 2.463965,
			"shared": false,
			"zoom": 1.6
		  }
		},
		"pluginVersion": "9.2.4",
		"targets": [
		  {
			"datasource": {
			  "type": "prometheus",
			  "uid": "${DS_PROMETHEUS}"
			},
			"editorMode": "code",
			"exemplar": false,
			"expr": "geoip{}",
			"format": "table",
			"instant": false,
			"interval": "",
			"legendFormat": "{{city}}",
			"range": true,
			"refId": "A"
		  }
		],
		"title": "Networth World Map",
		"transparent": true,
		"type": "geomap"
	  },
	  {
		"datasource": {
		  "type": "prometheus",
		  "uid": "${DS_PROMETHEUS}"
		},
		"fieldConfig": {
		  "defaults": {
			"color": {
			  "mode": "palette-classic"
			},
			"custom": {
			  "axisCenteredZero": false,
			  "axisColorMode": "text",
			  "axisGridShow": false,
			  "axisLabel": "Bytes",
			  "axisPlacement": "auto",
			  "barAlignment": 0,
			  "drawStyle": "line",
			  "fillOpacity": 0,
			  "gradientMode": "none",
			  "hideFrom": {
				"legend": false,
				"tooltip": false,
				"viz": false
			  },
			  "lineInterpolation": "smooth",
			  "lineStyle": {
				"fill": "solid"
			  },
			  "lineWidth": 4,
			  "pointSize": 1,
			  "scaleDistribution": {
				"type": "linear"
			  },
			  "showPoints": "auto",
			  "spanNulls": false,
			  "stacking": {
				"group": "A",
				"mode": "none"
			  },
			  "thresholdsStyle": {
				"mode": "off"
			  }
			},
			"mappings": [],
			"thresholds": {
			  "mode": "absolute",
			  "steps": [
				{
				  "color": "green",
				  "value": null
				},
				{
				  "color": "red",
				  "value": 80
				}
			  ]
			}
		  },
		  "overrides": []
		},
		"gridPos": {
		  "h": 11,
		  "w": 8,
		  "x": 16,
		  "y": 0
		},
		"id": 2,
		"options": {
		  "legend": {
			"calcs": [],
			"displayMode": "list",
			"placement": "bottom",
			"showLegend": false
		  },
		  "timezone": [
			"browser"
		  ],
		  "tooltip": {
			"mode": "single",
			"sort": "asc"
		  }
		},
		"targets": [
		  {
			"datasource": {
			  "type": "prometheus",
			  "uid": "${DS_PROMETHEUS}"
			},
			"editorMode": "builder",
			"expr": "sum(bytes_per_ip)",
			"legendFormat": "__auto",
			"range": true,
			"refId": "A"
		  }
		],
		"title": "Total Bytes Recieved",
		"transparent": true,
		"type": "timeseries"
	  },
	  {
		"datasource": {
		  "type": "prometheus",
		  "uid": "${DS_PROMETHEUS}"
		},
		"description": "",
		"fieldConfig": {
		  "defaults": {
			"color": {
			  "mode": "palette-classic"
			},
			"custom": {
			  "hideFrom": {
				"legend": false,
				"tooltip": false,
				"viz": false
			  }
			},
			"mappings": []
		  },
		  "overrides": []
		},
		"gridPos": {
		  "h": 9,
		  "w": 8,
		  "x": 16,
		  "y": 11
		},
		"id": 8,
		"options": {
		  "displayLabels": [
			"percent"
		  ],
		  "legend": {
			"displayMode": "table",
			"placement": "right",
			"showLegend": true,
			"values": [
			  "percent"
			]
		  },
		  "pieType": "donut",
		  "reduceOptions": {
			"calcs": [
			  "lastNotNull"
			],
			"fields": "",
			"values": false
		  },
		  "tooltip": {
			"mode": "single",
			"sort": "none"
		  }
		},
		"targets": [
		  {
			"datasource": {
			  "type": "prometheus",
			  "uid": "${DS_PROMETHEUS}"
			},
			"editorMode": "builder",
			"expr": "protocol_data_total",
			"format": "heatmap",
			"legendFormat": "{{protocol}}",
			"range": true,
			"refId": "A"
		  }
		],
		"title": "IP Protocols",
		"transparent": true,
		"type": "piechart"
	  },
	  {
		"datasource": {
		  "type": "prometheus",
		  "uid": "${DS_PROMETHEUS}"
		},
		"fieldConfig": {
		  "defaults": {
			"mappings": [],
			"thresholds": {
			  "mode": "percentage",
			  "steps": [
				{
				  "color": "green",
				  "value": null
				},
				{
				  "color": "orange",
				  "value": 70
				},
				{
				  "color": "red",
				  "value": 85
				}
			  ]
			}
		  },
		  "overrides": []
		},
		"gridPos": {
		  "h": 4,
		  "w": 4,
		  "x": 16,
		  "y": 20
		},
		"id": 6,
		"options": {
		  "orientation": "auto",
		  "reduceOptions": {
			"calcs": [
			  "lastNotNull"
			],
			"fields": "",
			"values": false
		  },
		  "showThresholdLabels": false,
		  "showThresholdMarkers": true
		},
		"pluginVersion": "9.2.4",
		"targets": [
		  {
			"datasource": {
			  "type": "prometheus",
			  "uid": "${DS_PROMETHEUS}"
			},
			"editorMode": "builder",
			"expr": "rate(process_cpu_seconds_total[15s]) * 100",
			"legendFormat": "__auto",
			"range": true,
			"refId": "A"
		  }
		],
		"title": "CPU % used by NetWorth",
		"transparent": true,
		"type": "gauge"
	  }
	],
	"refresh": false,
	"schemaVersion": 37,
	"style": "dark",
	"tags": [],
	"templating": {
	  "list": []
	},
	"time": {
	  "from": "now-30m",
	  "to": "now"
	},
	"timepicker": {},
	"timezone": "",
	"title": "Networth",
	"uid": "PyIm36vVk",
	"version": 12,
	"weekStart": ""
  }